{"type": "scene", "properties": {"baseExtent": {"cx": 536329.5223030054, "cy": 4492085.890300367, "width": 142.87500014458783, "height": 142.87500014458783, "rotation": 0}, "origin": {"x": 536329.5223030054, "y": 4492085.890300367, "z": 0.0}, "zScale": 1.0, "light": "directional", "proj": "+proj=utm +zone=33 +datum=WGS84 +units=m +no_defs"}, "layers": [{"type": "layer", "id": 0, "properties": {"name": "Riproiettato", "clickable": true, "visible": true, "type": "line", "objType": "Line"}, "data": {"materials": [{"type": 3, "c": 15167816, "dashed": false}], "blocks": [{"url": "./data/index/a0.json", "featureCount": 1}]}}, {"type": "layer", "id": 3, "properties": {"name": "Flat Plane", "clickable": true, "visible": true, "type": "dem", "clipped": false, "mtlNames": ["map (canvas)"], "mtlIdx": 0}, "data": [{"type": "block", "layer": 3, "block": 0, "materials": [{"type": 0, "image": {"url": "./data/index/b0.png"}, "ds": 1, "mtlIndex": 0, "useNow": true}]}, {"type": "block", "layer": 3, "block": 0, "width": 142.87500014458783, "height": 142.87500014458783, "translate": [0.0, 0.0, 0], "zScale": 1.0, "grid": {"width": 2, "height": 2, "url": "./data/index/b0.bin"}}]}]}